stat3255demo/__init__.py
stat3255demo/demo.py
stat3255demo-0.1.0.dist-info/METADATA
stat3255demo-0.1.0.dist-info/WHEEL
stat3255demo-0.1.0.dist-info/top_level.txt
stat3255demo-0.1.0.dist-info/RECORD
